sorthosts/__init__.py
sorthosts-0.1.2.dist-info/METADATA
sorthosts-0.1.2.dist-info/WHEEL
sorthosts-0.1.2.dist-info/entry_points.txt
sorthosts-0.1.2.dist-info/licenses/LICENSE
sorthosts-0.1.2.dist-info/RECORD
