Metadata-Version: 2.4
Name: sorthosts
Version: 0.1.2
Summary: Sort ssh known_hosts file.
Project-URL: homepage, https://github.com/darkclip/sorthosts
Project-URL: repository, https://github.com/darkclip/sorthosts
Project-URL: documentation, https://github.com/darkclip/sorthosts
Author-email: darkclip <darkclip@hanv.dev>
License-Expression: MIT
License-File: LICENSE
Keywords: hosts,known_hosts,sort,ssh
Requires-Python: >=3.8
